thendisnever/__init__.py
thendisnever/test_thend.py
thendisnever/thend.py
thendisnever-0.10.0.dist-info/LICENSE
thendisnever-0.10.0.dist-info/METADATA
thendisnever-0.10.0.dist-info/WHEEL
thendisnever-0.10.0.dist-info/entry_points.txt
thendisnever-0.10.0.dist-info/RECORD
