Metadata-Version: 2.1
Name: thendisnever
Version: 0.10.0
Summary: A package to easily make an LLM talk with itself forever.
Home-page: https://github.com/andrewhinh/thendisnever
License: MIT
Author: Andrew Hinh
Author-email: ajhinh@gmail.com
Requires-Python: >=3.8,<4.0
Classifier: License :: OSI Approved :: MIT License
Classifier: Programming Language :: Python :: 3
Classifier: Programming Language :: Python :: 3.8
Classifier: Programming Language :: Python :: 3.9
Classifier: Programming Language :: Python :: 3.10
Classifier: Programming Language :: Python :: 3.11
Requires-Dist: torch (>=2.0.0,<3.0.0)
Requires-Dist: transformers (>=4.0.0,<5.0.0)
Requires-Dist: typer[all] (>=0.9.0,<0.10.0)
Project-URL: Repository, https://github.com/andrewhinh/thendisnever
Project-URL: issues, https://github.com/andrewhinh/thendisnever/issues
